web3r/__init__.py
web3r/main.py
web3r/concurrency/__init__.py
web3r/concurrency/concurrency.py
web3r/datatypes/__init__.py
web3r/datatypes/the_graph_uniV3.py
web3r/datatypes/token.py
web3r/datatypes/transfer.py
web3r/exeptions/__init__.py
web3r/exeptions/exeptions.py
web3r/pricer/__init__.py
web3r/pricer/pricer.py
web3r/pricer/uniswapV2.py
web3r/pricer/uniswapV3.py
web3r/the_graph_uniswapV3/__init__.py
web3r/the_graph_uniswapV3/the_graph_uniswapV3.py
web3r/tokens/__init__.py
web3r/tokens/tokens.py
web3r/utils/__init__.py
web3r/utils/utils.py
web3r-0.0.4.dist-info/LICENSE
web3r-0.0.4.dist-info/METADATA
web3r-0.0.4.dist-info/WHEEL
web3r-0.0.4.dist-info/top_level.txt
web3r-0.0.4.dist-info/RECORD
